grappa/__init__.py
grappa/api.py
grappa/assertion.py
grappa/base.py
grappa/config.py
grappa/constants.py
grappa/context.py
grappa/decorators.py
grappa/empty.py
grappa/engine.py
grappa/exceptions.py
grappa/log.py
grappa/operator.py
grappa/operator_dsl.py
grappa/plugin.py
grappa/reporter.py
grappa/resolver.py
grappa/runner.py
grappa/template.py
grappa/test.py
grappa/test_proxy.py
grappa/operators/__init__.py
grappa/operators/attributes.py
grappa/operators/been_called.py
grappa/operators/been_called_with.py
grappa/operators/bool.py
grappa/operators/callable.py
grappa/operators/contain.py
grappa/operators/empty.py
grappa/operators/equal.py
grappa/operators/implements.py
grappa/operators/index.py
grappa/operators/keys.py
grappa/operators/length.py
grappa/operators/match.py
grappa/operators/none.py
grappa/operators/only.py
grappa/operators/pass_test.py
grappa/operators/present.py
grappa/operators/property.py
grappa/operators/raises.py
grappa/operators/range.py
grappa/operators/start_end.py
grappa/operators/type.py
grappa/operators/within.py
grappa/reporters/__init__.py
grappa/reporters/assertion.py
grappa/reporters/base.py
grappa/reporters/code.py
grappa/reporters/diff.py
grappa/reporters/error.py
grappa/reporters/expected.py
grappa/reporters/information.py
grappa/reporters/message.py
grappa/reporters/reasons.py
grappa/reporters/subject.py
tests/operators/__init__.py
tests/operators/attributes_test.py
tests/operators/been_called_test.py
tests/operators/bool_test.py
tests/operators/callable_test.py
tests/operators/conftest.py
tests/operators/contain_test.py
tests/operators/empty_test.py
tests/operators/implements_test.py
tests/operators/index_test.py
tests/operators/keys_test.py
tests/operators/length_test.py
tests/operators/none_test.py
tests/operators/only_test.py
tests/operators/pass_test.py
tests/operators/present_test.py
tests/operators/properties_test.py
tests/operators/raises_test.py
tests/operators/range_test.py
tests/operators/start_end_test.py
grappa-1.0.1.dist-info/AUTHORS
grappa-1.0.1.dist-info/LICENSE
grappa-1.0.1.dist-info/METADATA
grappa-1.0.1.dist-info/WHEEL
grappa-1.0.1.dist-info/top_level.txt
grappa-1.0.1.dist-info/RECORD
